jenkins_jobs/__init__.py
jenkins_jobs/builder.py
jenkins_jobs/cmd.py
jenkins_jobs/constants.py
jenkins_jobs/errors.py
jenkins_jobs/formatter.py
jenkins_jobs/local_yaml.py
jenkins_jobs/parser.py
jenkins_jobs/registry.py
jenkins_jobs/utils.py
jenkins_jobs/version.py
jenkins_jobs/xml_config.py
jenkins_jobs/modules/__init__.py
jenkins_jobs/modules/base.py
jenkins_jobs/modules/builders.py
jenkins_jobs/modules/general.py
jenkins_jobs/modules/helpers.py
jenkins_jobs/modules/hipchat_notif.py
jenkins_jobs/modules/hudson_model.py
jenkins_jobs/modules/metadata.py
jenkins_jobs/modules/notifications.py
jenkins_jobs/modules/parameters.py
jenkins_jobs/modules/project_flow.py
jenkins_jobs/modules/project_freestyle.py
jenkins_jobs/modules/project_matrix.py
jenkins_jobs/modules/project_maven.py
jenkins_jobs/modules/project_multijob.py
jenkins_jobs/modules/properties.py
jenkins_jobs/modules/publishers.py
jenkins_jobs/modules/reporters.py
jenkins_jobs/modules/scm.py
jenkins_jobs/modules/triggers.py
jenkins_jobs/modules/wrappers.py
jenkins_jobs/modules/zuul.py
jenkins_jobs/sphinx/__init__.py
jenkins_jobs/sphinx/yaml.py
jjb_puppetlabs-1.2.1.dev145.dist-info/DESCRIPTION.rst
jjb_puppetlabs-1.2.1.dev145.dist-info/METADATA
jjb_puppetlabs-1.2.1.dev145.dist-info/RECORD
jjb_puppetlabs-1.2.1.dev145.dist-info/WHEEL
jjb_puppetlabs-1.2.1.dev145.dist-info/entry_points.txt
jjb_puppetlabs-1.2.1.dev145.dist-info/metadata.json
jjb_puppetlabs-1.2.1.dev145.dist-info/pbr.json
jjb_puppetlabs-1.2.1.dev145.dist-info/top_level.txt
