Metadata-Version: 2.0
Name: jjb-puppetlabs
Version: 1.2.1.dev145
Summary: Manage Jenkins jobs with YAML, PuppetLabs experimental package
Home-page: http://docs.openstack.org/infra/system-config/jjb.html
Author: Wayne Warren
Author-email: waynr+pypi@sdf.org
License: Apache License, Version 2.0
Platform: UNKNOWN
Classifier: Topic :: Utilities
Classifier: Environment :: Console
Classifier: Intended Audience :: Developers
Classifier: Intended Audience :: Information Technology
Classifier: Intended Audience :: System Administrators
Classifier: License :: OSI Approved :: Apache Software License
Classifier: Operating System :: OS Independent
Classifier: Programming Language :: Python
Classifier: Programming Language :: Python :: 2
Classifier: Programming Language :: Python :: 2.6
Classifier: Programming Language :: Python :: 2.7
Classifier: Programming Language :: Python :: 3
Classifier: Programming Language :: Python :: 3.3
Requires-Dist: PyYAML
Requires-Dist: argparse
Requires-Dist: ordereddict
Requires-Dist: pbr (>=0.8.2,<2.0)
Requires-Dist: python-jenkins (==0.4.8)
Requires-Dist: six (>=1.5.2)
